<Properties StartupConfiguration="{5927F3FF-EC9A-47E8-86C4-70E4BA6E7490}|Default">
  <MonoDevelop.Ide.Workbench ActiveDocument="YourDrink/FavoritePage.xaml.cs">
    <Files>
      <File FileName="YourDrink/Redefinitions/CustomViewCell.cs" Line="45" Column="7" IsPinned="True" />
      <File FileName="YourDrink/CategoryListPage.xaml" />
      <File FileName="YourDrink/CategoryListPage.xaml.cs" />
      <File FileName="YourDrink.Android/CustomViewCellRenderer.cs" />
      <File FileName="YourDrink/Base64ImageConverter.cs" />
      <File FileName="YourDrink.Android/CustomListViewRenderer.cs" />
      <File FileName="YourDrink/DrinkPage.xaml" />
      <File FileName="YourDrink/DrinkPage.xaml.cs" />
      <File FileName="YourDrink/MainPage.xaml.cs" Line="1" Column="1" />
      <File FileName="YourDrink/MasterDetail.xaml.cs" Line="1" Column="1" />
      <File FileName="YourDrink/MasterDetail.xaml" />
      <File FileName="YourDrink/MainPage.xaml" />
      <File FileName="YourDrink/DetailPage.xaml.cs" />
      <File FileName="YourDrink/DetailPage.xaml" />
      <File FileName="YourDrink/Favorite.cs" />
      <File FileName="YourDrink/CreateDrinkPage.xaml.cs" Line="85" Column="52" />
      <File FileName="YourDrink/Model/Category.cs" />
      <File FileName="YourDrink/Model/DrinkWithImage.cs" />
      <File FileName="YourDrink.Android/Resources/drawable/baseline_grade_white_24.png" />
      <File FileName="YourDrink/PostPage.xaml" Line="4" Column="20" />
      <File FileName="YourDrink/Model/Post.cs" />
      <File FileName="YourDrink/PostPage.xaml.cs" Line="20" Column="27" />
      <File FileName="YourDrink.Android/MainActivity.cs" />
      <File FileName="YourDrink/FormatAmount.cs" Line="1" Column="1" />
      <File FileName="YourDrink/FavoritePage.xaml.cs" Line="1" Column="1" />
    </Files>
    <Pads>
      <Pad Id="ProjectPad">
        <State name="__root__">
          <Node name="YourDrink" expanded="True">
            <Node name="YourDrink" expanded="True">
              <Node name="Dependencies" expanded="True">
                <Node name="PackageDependencies" expanded="True" />
              </Node>
              <Node name="Model" expanded="True" />
              <Node name="Redefinitions" expanded="True" />
              <Node name="App.xaml" expanded="True" />
              <Node name="CategoryListPage.xaml" expanded="True" />
              <Node name="CreateDrinkPage.xaml" expanded="True" />
              <Node name="DetailPage.xaml" expanded="True" />
              <Node name="DrinkPage.xaml" expanded="True" />
              <Node name="FavoritePage.xaml" expanded="True">
                <Node name="FavoritePage.xaml.cs" selected="True" />
              </Node>
              <Node name="MainPage.xaml" expanded="True" />
              <Node name="MasterDetail.xaml" expanded="True" />
              <Node name="PostPage.xaml" expanded="True" />
            </Node>
            <Node name="YourDrink.Android" expanded="True">
              <Node name="Assets" expanded="True" />
              <Node name="Properties" expanded="True" />
              <Node name="Resources" expanded="True">
                <Node name="drawable" expanded="True" />
                <Node name="layout" expanded="True" />
                <Node name="values" expanded="True" />
              </Node>
            </Node>
          </Node>
        </State>
      </Pad>
    </Pads>
  </MonoDevelop.Ide.Workbench>
  <MonoDevelop.Ide.ItemProperties.YourDrink.Android AndroidDesignerPreferredTheme="Theme.AppCompat.Light.NoActionBar" AndroidDesignerPreferredDevice="Nexus 4" PreferredExecutionTarget="Android.Android_Accelerated_Oreo" />
  <MonoDevelop.Ide.DebuggingService.PinnedWatches />
  <MonoDevelop.Ide.Workspace ActiveConfiguration="Debug" />
  <Debugger.DebugSourceFolders>
    <String>/Users/preyde/Library/Caches/VisualStudio/8.0/Symbols/mono/mono/c0c5c78e2bdbdbf7a70ae10b0a698708f1f2edbe</String>
  </Debugger.DebugSourceFolders>
  <MonoDevelop.Ide.DebuggingService.Breakpoints>
    <BreakpointStore />
  </MonoDevelop.Ide.DebuggingService.Breakpoints>
  <MultiItemStartupConfigurations />
</Properties>